Metadata-Version: 2.0
Name: odoo9-addon-stock-available-unreserved
Version: 9.0.1.0.0
Summary: Quantity of stock available for inmediate use
Home-page: https://www.odoo-community.org
Author: Eficent Business and IT Consulting Services S.L,Odoo Community Association (OCA)
Author-email: support@odoo-community.org
License: AGPL-3
Platform: UNKNOWN
Requires-Dist: odoo (<9.1a,>=9.0a)
Classifier: Programming Language :: Python :: 2.7
Classifier: Framework :: Odoo
Classifier: License :: OSI Approved :: GNU Affero General Public License v3
